bedwarspro/__init__.py
bedwarspro/client.py
bedwarspro/errors.py
bedwarspro/utils.py
bedwarspro/models/__init__.py
bedwarspro/models/player.py
bedwarspro-0.0.1.dist-info/METADATA
bedwarspro-0.0.1.dist-info/WHEEL
bedwarspro-0.0.1.dist-info/top_level.txt
bedwarspro-0.0.1.dist-info/RECORD
