Metadata-Version: 2.1
Name: bedwarspro
Version: 0.0.1
Summary: A Python wrapper for the Bedwars Pro API
Home-page: https://github.com/Co0kei
Author: Co0kei
License: MIT
Platform: UNKNOWN
Requires-Dist: aiohttp (>=3.6.0)
